flake8_slots/__init__.py
flake8_slots/py.typed
flake8_slots-0.1.6.dist-info/LICENSE
flake8_slots-0.1.6.dist-info/METADATA
flake8_slots-0.1.6.dist-info/WHEEL
flake8_slots-0.1.6.dist-info/entry_points.txt
flake8_slots-0.1.6.dist-info/RECORD
