Metadata-Version: 2.1
Name: flake8-slots
Version: 0.1.6
Summary: A Flake8 plugin to require __slots__ to be defined for subclasses of immutable types.
Author-email: Dominic Davis-Foster <dominic@davis-foster.co.uk>
License: MIT
Keywords: flake8
Home-page: https://github.com/python-formate/flake8-slots
Project-URL: Issue Tracker, https://github.com/python-formate/flake8-slots/issues
Project-URL: Source Code, https://github.com/python-formate/flake8-slots
Project-URL: Documentation, https://flake8-slots.readthedocs.io/en/latest
Platform: Windows
Platform: macOS
Platform: Linux
Classifier: Development Status :: 4 - Beta
Classifier: Framework :: Flake8
Classifier: Intended Audience :: Developers
Classifier: License :: OSI Approved :: MIT License
Classifier: Operating System :: OS Independent
Classifier: Programming Language :: Python
Classifier: Programming Language :: Python :: 3 :: Only
Classifier: Programming Language :: Python :: 3.6
Classifier: Programming Language :: Python :: 3.7
Classifier: Programming Language :: Python :: 3.8
Classifier: Programming Language :: Python :: 3.9
Classifier: Programming Language :: Python :: 3.10
Classifier: Programming Language :: Python :: 3.11
Classifier: Programming Language :: Python :: 3.12
Classifier: Programming Language :: Python :: Implementation :: CPython
Classifier: Programming Language :: Python :: Implementation :: PyPy
Classifier: Topic :: Utilities
Classifier: Typing :: Typed
Requires-Python: >=3.6
Requires-Dist: flake8>=3.8.4
Requires-Dist: flake8-helper>=0.1.1
